AUTHORS.txt
CHANGES.txt
LICENSE.txt
MANIFEST.in
README.txt
setup.py
tipfy/__init__.py
tipfy/app.py
tipfy/config.py
tipfy/dev.py
tipfy/i18n.py
tipfy/middleware.py
tipfy/routing.py
tipfy/scripting.py
tipfy/sessions.py
tipfy/template.py
tipfy/testing.py
tipfy/utils.py
tipfy/appengine/__init__.py
tipfy/appengine/acl.py
tipfy/appengine/blobstore.py
tipfy/appengine/mail.py
tipfy/appengine/matcher.py
tipfy/appengine/sessions.py
tipfy/appengine/sharded_counter.py
tipfy/appengine/taskqueue.py
tipfy/appengine/xmpp.py
tipfy/appengine/auth/__init__.py
tipfy/appengine/auth/model.py
tipfy/appengine/db/__init__.py
tipfy/appengine/db/properties.py
tipfy/auth/__init__.py
tipfy/auth/facebook.py
tipfy/auth/friendfeed.py
tipfy/auth/google.py
tipfy/auth/oauth.py
tipfy/auth/openid.py
tipfy/auth/twitter.py
tipfy/debugger/__init__.py
tipfy/debugger/templates/console.html
tipfy/debugger/templates/dump_object.html
tipfy/debugger/templates/frame.html
tipfy/debugger/templates/help_command.html
tipfy/debugger/templates/source.html
tipfy/debugger/templates/traceback_full.html
tipfy/debugger/templates/traceback_plaintext.html
tipfy/debugger/templates/traceback_summary.html
tipfy_dev.egg-info/PKG-INFO
tipfy_dev.egg-info/SOURCES.txt
tipfy_dev.egg-info/dependency_links.txt
tipfy_dev.egg-info/entry_points.txt
tipfy_dev.egg-info/namespace_packages.txt
tipfy_dev.egg-info/not-zip-safe
tipfy_dev.egg-info/requires.txt
tipfy_dev.egg-info/top_level.txt
tipfyext/__init__.py
tipfyext/mako.py
tipfyext/appengine/__init__.py
tipfyext/jinja2/__init__.py
tipfyext/jinja2/scripts.py
tipfyext/wtforms/__init__.py
tipfyext/wtforms/fields.py
tipfyext/wtforms/form.py
tipfyext/wtforms/validators.py
tipfyext/wtforms/widgets.py