Metadata-Version: 1.0
Name: tipfy-dev
Version: 1.8
Summary: The almighty little framework for Google App Engine
Home-page: http://www.tipfy.org/
Author: Rodrigo Moraes
Author-email: rodrigo.moraes@gmail.com
License: BSD
Download-URL: http://www.tipfy.org/tipfy.tar.gz
Platform: any
Classifier: Development Status :: 5 - Production/Stable
Classifier: Environment :: Web Environment
Classifier: Intended Audience :: Developers
Classifier: License :: OSI Approved :: BSD License
Classifier: Operating System :: OS Independent
Classifier: Programming Language :: Python
Classifier: Topic :: Internet :: WWW/HTTP :: Dynamic Content
Classifier: Topic :: Software Development :: Libraries :: Python Modules
